strdrop/__init__.py
strdrop/cli/__init__.py
strdrop/cli/main.py
strdrop/drops/__init__.py
strdrop/drops/annotate.py
strdrop/drops/calculate.py
strdrop-0.3.2.dist-info/METADATA
strdrop-0.3.2.dist-info/WHEEL
strdrop-0.3.2.dist-info/entry_points.txt
strdrop-0.3.2.dist-info/licenses/LICENSE
strdrop-0.3.2.dist-info/RECORD
