Metadata-Version: 2.4
Name: strdrop
Version: 0.3.2
Summary: Detect coverage drops in LRS STR expansion calls
Project-URL: Repository, https://github.com/dnil/strdrop
Project-URL: Changelog, https://github.com/dnil/strdrop/blob/main/CHANGELOG.md
Project-URL: Documentation, https://dnil.github.io/strdrop/
Project-URL: Bug Tracker, https://github.com/dnil/strdrop/issues
Project-URL: Issues, https://github.com/dnile/strdrop/issues
Author-email: Daniel Nilsson <daniel.nilsson@ki.se>, Egor Dolzhenko <edolzhenko@pacificbiosciences.com>
License: MIT License
License-File: LICENSE
Keywords: coverage,dna,lrs,str,variants,vcf
Classifier: Development Status :: 3 - Alpha
Classifier: Intended Audience :: Developers
Classifier: Intended Audience :: Science/Research
Classifier: License :: OSI Approved :: MIT License
Classifier: Operating System :: MacOS :: MacOS X
Classifier: Operating System :: Unix
Classifier: Programming Language :: Python
Classifier: Programming Language :: Python :: 3.10
Classifier: Programming Language :: Python :: 3.11
Classifier: Programming Language :: Python :: 3.12
Classifier: Programming Language :: Python :: 3.13
Classifier: Programming Language :: Python :: 3.14
Classifier: Programming Language :: Python :: Implementation :: CPython
Classifier: Topic :: Scientific/Engineering :: Bio-Informatics
Classifier: Topic :: Scientific/Engineering :: Medical Science Apps.
Requires-Python: >=3.10
Requires-Dist: coloredlogs
Requires-Dist: cyvcf2
Requires-Dist: pandas
Requires-Dist: python-levenshtein
Requires-Dist: typer
